pyonly/__init__.py
pyonly/document.py
pyonly/handler.py
pyonly-0.1.dist-info/LICENSE
pyonly-0.1.dist-info/METADATA
pyonly-0.1.dist-info/NOTICE.txt
pyonly-0.1.dist-info/WHEEL
pyonly-0.1.dist-info/top_level.txt
pyonly-0.1.dist-info/RECORD
