Metadata-Version: 2.1
Name: pyonly
Version: 0.1
Summary: Create interactive web UIs with Python instead of JavaScript!
Home-page: http://pyonly.com/
Author: Bennet Meyer
License: UNKNOWN
Platform: UNKNOWN
Classifier: Programming Language :: Python :: 3
Classifier: License :: OSI Approved :: Apache Software License
Classifier: Operating System :: OS Independent
Requires-Python: >=3.5
